pyrolific/__init__.py
pyrolific/api/__init__.py
pyrolific/api/bonuses/__init__.py
pyrolific/api/bonuses/create_bonus_payments.py
pyrolific/api/bonuses/pay_bonus_payments.py
pyrolific/api/eligibility_requirements/__init__.py
pyrolific/api/eligibility_requirements/get_eligibility_requirements.py
pyrolific/api/filter_sets/__init__.py
pyrolific/api/filter_sets/clone_filter_set.py
pyrolific/api/filter_sets/create_filter_set.py
pyrolific/api/filter_sets/delete_filter_set.py
pyrolific/api/filter_sets/get_filter_set.py
pyrolific/api/filter_sets/get_filter_sets.py
pyrolific/api/filter_sets/lock_filter_set.py
pyrolific/api/filter_sets/unlock_filter_set.py
pyrolific/api/filter_sets/update_filter_set.py
pyrolific/api/filters/__init__.py
pyrolific/api/filters/get_eligible_count.py
pyrolific/api/filters/get_filters.py
pyrolific/api/hooks/__init__.py
pyrolific/api/hooks/confirm_subscription.py
pyrolific/api/hooks/create_secret.py
pyrolific/api/hooks/create_subscription.py
pyrolific/api/hooks/delete_subscription.py
pyrolific/api/hooks/get_event_types.py
pyrolific/api/hooks/get_events.py
pyrolific/api/hooks/get_secrets.py
pyrolific/api/hooks/get_subscription.py
pyrolific/api/hooks/get_subscriptions.py
pyrolific/api/hooks/update_subscription.py
pyrolific/api/invitations/__init__.py
pyrolific/api/invitations/create_invitation.py
pyrolific/api/messages/__init__.py
pyrolific/api/messages/get_messages.py
pyrolific/api/messages/get_unread_messages.py
pyrolific/api/messages/post_api_v1_messages_bulk.py
pyrolific/api/messages/send_message.py
pyrolific/api/participant_groups/__init__.py
pyrolific/api/participant_groups/add_to_participant_group.py
pyrolific/api/participant_groups/create_participant_group.py
pyrolific/api/participant_groups/delete_participant_group.py
pyrolific/api/participant_groups/get_participant_group.py
pyrolific/api/participant_groups/get_participant_group_participants.py
pyrolific/api/participant_groups/get_participant_groups.py
pyrolific-1.5.1.dist-info/METADATA
pyrolific-1.5.1.dist-info/WHEEL
pyrolific-1.5.1.dist-info/RECORD
